Metadata-Version: 2.1
Name: TvShaBot
Version: 0.0.6
Summary: A bot to request a show info
Home-page: UNKNOWN
Author: ShaeNaZar
License: UNKNOWN
Platform: UNKNOWN
License-File: LICENSE
